{"version":"1.12","events":[{"event":"call","http_server_request":{"path_info":"/src/assets/index.js","request_method":"GET","headers":{"Host":"localhost:5173","Accept":"*/*","Origin":"http://localhost:5173","Accept-Encoding":"gzip, deflate","Connection":"keep-alive","Sec-Fetch-Mode":"cors","Sec-Fetch-Site":"same-origin","User-Agent":"Mozilla/5.0 (Macintosh; Intel Mac OS X 10_15_7) AppleWebKit/605.1.15 (KHTML, like Gecko) Version/18.1.1 Safari/605.1.15","Referer":"http://localhost:5173/","Sec-Fetch-Dest":"script","Accept-Language":"en-US,en;q=0.9"},"protocol":"HTTP/1.1"},"id":1,"thread_id":0},{"event":"return","http_server_response":{"status_code":200,"headers":{"Access-Control-Allow-Origin":"*","Content-Type":"application/javascript","Cache-Control":"no-cache","Etag":"W/\"889-jZHb6mgO7955XbRil1K50T5DNm8\""},"return_value":{"class":"[ResponseBody]","value":"import logo from \"/src/assets/logo.svg?import\";\nimport logo1 from \"/src/assets/logo1.png?import\";\nimport backend from \"/src/assets/backend.png?import\";\nimport creator from \"/src/assets/creator.png?import\";\nimport mobile from \"/src/assets/mobile.png?import\";\nimport web from \"/src/assets/web.png?import\";\nimport github from \"/src/assets/github.png?import\";\nimport menu from \"/src/assets/menu.svg?import\";\nimport close from \"/src/assets/close.svg?import\";\n\nimport css from \"/src/assets/tech/css.png?import\";\nimport docker from \"/src/assets/tech/docker.png?import\";\nimport figma from \"/src/assets/tech/figma.png?import\";\nimport git from \"/src/assets/tech/git.png?import\";\nimport html from \"/src/assets/tech/html.png?import\";\nimport javascript from \"/src/assets/tech/javascript.png?import\";\nimport mongodb from \"/src/assets/tech/mongodb.png?import\";\nimport nodejs from \"/src/assets/tech/nodejs.png?import\";\nimport reactjs from \"/src/assets/tech/reactjs.png?import\";\nimport redux from \"/src/assets/tech/redux.png?import\";\nimport apple from \"/src/assets/tech/apple.png?import\";\nimport apple1 from \"/src/assets/tech/apple1.png?import\";\nimport swift from \"/src/assets/tech/swift.png?import\";\nimport tailwind from \"/src/assets/tech/tailwind.png?import\";\nimport typescript from \"/src/assets/tech/typescript.png?import\";\nimport threejs from \"/src/assets/tech/threejs.svg?import\";\n\nimport meta from \"/src/assets/company/meta.png?import\";\nimport shopify from \"/src/assets/company/shopify.png?import\";\nimport starbucks from \"/src/assets/company/starbucks.png?import\";\nimport codefeast from \"/src/assets/company/codefeast.png?import\";\nimport tesla from \"/src/assets/company/tesla.png?import\";\n\nimport carrent from \"/src/assets/carrent.png?import\";\nimport jobit from \"/src/assets/jobit.png?import\";\nimport tripguide from \"/src/assets/tripguide.png?import\";\n\nexport {\n  logo1,\n  logo,\n  backend,\n  creator,\n  mobile,\n  web,\n  github,\n  menu,\n  close,\n  css,\n  docker,\n  figma,\n  git,\n  html,\n  javascript,\n  mongodb,\n  nodejs,\n  reactjs,\n  redux,\n  apple,\n  apple1,\n  swift,\n  tailwind,\n  typescript,\n  threejs,\n  meta,\n  shopify,\n  starbucks,\n  codefeast,\n  tesla,\n  carrent,\n  jobit,\n  tripguide,\n};\n"}},"id":2,"thread_id":0,"parent_id":1,"elapsed":0.00016262498684227467}],"classMap":[],"metadata":{"client":{"name":"appmap-node","version":"2.24.3","url":"https://github.com/getappmap/appmap-node"},"language":{"name":"javascript","engine":"Node.js","version":"v23.3.0"},"app":"3dfolio","recorder":{"type":"requests","name":"requests"},"name":"GET /src/assets/index.js (200) — 2024-12-01T15:09:00.102Z"}}